pyhpo/__init__.py
pyhpo/annotations.py
pyhpo/config.py
pyhpo/matrix.py
pyhpo/ontology.py
pyhpo/set.py
pyhpo/stats.py
pyhpo/term.py
pyhpo/update_data.py
pyhpo/data/genes_to_phenotype.txt
pyhpo/data/hp.obo
pyhpo/data/phenotype.hpoa
pyhpo/data/phenotype_to_genes.txt
pyhpo/parser/__init__.py
pyhpo/parser/diseases.py
pyhpo/parser/generics.py
pyhpo/parser/genes.py
pyhpo/parser/obo.py
pyhpo/similarity/__init__.py
pyhpo/similarity/base.py
pyhpo/similarity/defaults.py
pyhpo-4.0.0.dist-info/LICENSE
pyhpo-4.0.0.dist-info/METADATA
pyhpo-4.0.0.dist-info/WHEEL
pyhpo-4.0.0.dist-info/top_level.txt
pyhpo-4.0.0.dist-info/RECORD
