Metadata-Version: 2.1
Name: pyhpo
Version: 4.0.0
Summary: A Python package to work with the HPO Ontology
Home-page: https://github.com/anergictcell/pyhpo
Author-email: Jonas Marcello <jonas.marcello@esbme.com>
License: MIT
Project-URL: Homepage, https://github.com/anergictcell/pyhpo
Project-URL: Repository, https://github.com/anergictcell/pyhpo
Project-URL: Bug Tracker, https://github.com/anergictcell/pyhpo/issues
Project-URL: Documentation, https://pyhpo.readthedocs.io/
Keywords: hpo,phenotype,genotype,bioinformatics,rare diseases
Platform: UNKNOWN
Classifier: Programming Language :: Python :: Implementation :: CPython
Classifier: Programming Language :: Python :: Implementation :: PyPy
Classifier: Intended Audience :: Developers
Classifier: Intended Audience :: Healthcare Industry
Classifier: Intended Audience :: Science/Research
Classifier: License :: OSI Approved :: MIT License
Classifier: Operating System :: OS Independent
Classifier: Topic :: Scientific/Engineering :: Bio-Informatics
Classifier: Topic :: Scientific/Engineering :: Medical Science Apps.
Classifier: Topic :: Software Development :: Libraries :: Python Modules
Requires-Python: >=3.8
Provides-Extra: scipy
Provides-Extra: all
Provides-Extra: dev
License-File: LICENSE
